<?xml version='1.0' encoding='UTF-8'?>
<song xmlns="http://openlyrics.info/namespace/2009/song" version="0.8" createdIn="OpenLP 3.1.3" modifiedIn="OpenLP 3.1.3" modifiedDate="2024-10-25T23:53:46">
  <properties>
    <titles>
      <title>Arise My Soul Arise</title>
    </titles>
    <copyright>Public Domain</copyright>
    <authors>
      <author>Charles Wesley Daniel B. Towner</author>
    </authors>
  </properties>
  <lyrics>
    <verse name="v1">
      <lines>Arise, my soul, arise, newline Shake off thy guilty fears; newline The bleeding sacrifice newline In my behalf appears; newline Before the throne my surety stands, newline My name is written on His hands, newline My name is written on His hands.</lines>
    </verse>
    <verse name="v2">
      <lines>He ever lives above, for me to intercede; newline His all redeeming love newline His precious blood to plead; newline His blood atoned for all our race, newline And sprinkles now the throne of grace, newline And sprinkles now the throne of grace.</lines>
    </verse>
    <verse name="v3">
      <lines>The Father hears Him pray, newline His dear Anointed One; newline He cannot turn away newline The presence of His Son: newline His Spirit answers to the blood, newline And tells me I am born of God, newline And tells me I am born of God.</lines>
    </verse>
    <verse name="v4">
      <lines>My God is reconciled, newline His pardoning voice I hear; newline He owns me for His child, newline I can no longer fear; newline With confidence I now draw nigh, newline And Father, Abba Father cry, newline And Father, Abba Father cry!</lines>
    </verse>
  </lyrics>
</song>
